drifters/__init__.py
drifters/admin.py
drifters/app_settings.py
drifters/auth_hooks.py
drifters/forms.py
drifters/models.py
drifters/routing.py
drifters/tasks.py
drifters/urls.py
drifters/views.py
drifters/cogs/drifters.py
drifters/locale/da_DK/LC_MESSAGES/django.mo
drifters/locale/da_DK/LC_MESSAGES/django.po
drifters/locale/de/LC_MESSAGES/django.mo
drifters/locale/de/LC_MESSAGES/django.po
drifters/locale/en/LC_MESSAGES/django.mo
drifters/locale/en/LC_MESSAGES/django.po
drifters/locale/es/LC_MESSAGES/django.mo
drifters/locale/es/LC_MESSAGES/django.po
drifters/locale/fr_FR/LC_MESSAGES/django.mo
drifters/locale/fr_FR/LC_MESSAGES/django.po
drifters/locale/it_IT/LC_MESSAGES/django.mo
drifters/locale/it_IT/LC_MESSAGES/django.po
drifters/locale/ja/LC_MESSAGES/django.mo
drifters/locale/ja/LC_MESSAGES/django.po
drifters/locale/ko_KR/LC_MESSAGES/django.mo
drifters/locale/ko_KR/LC_MESSAGES/django.po
drifters/locale/ru/LC_MESSAGES/django.mo
drifters/locale/ru/LC_MESSAGES/django.po
drifters/locale/uk/LC_MESSAGES/django.mo
drifters/locale/uk/LC_MESSAGES/django.po
drifters/locale/zh_Hans/LC_MESSAGES/django.mo
drifters/locale/zh_Hans/LC_MESSAGES/django.po
drifters/migrations/0001_initial.py
drifters/migrations/0002_clear.py
drifters/migrations/0003_wormhole_archived_wormhole_archived_at_and_more.py
drifters/migrations/0004_wormhole_bookmarked_k_wormhole_bookmarked_w_and_more.py
drifters/migrations/0005_alter_wormhole_archived_at_and_more.py
drifters/migrations/0006_alter_clear_system_alter_wormhole_system.py
drifters/migrations/0007_alter_clear_options_driftersconfiguration.py
drifters/migrations/0008_driftersconfiguration_motd_systems_and_more.py
drifters/migrations/0009_wormhole_reserved.py
drifters/migrations/0010_general_alter_wormhole_eol_changed_at_and_more.py
drifters/migrations/0011_alter_wormhole_managers.py
drifters/migrations/0012_alter_driftersconfiguration_poi_regions_and_more.py
drifters/migrations/__init__.py
drifters/templates/drifters/base.html
aa_drifters-0.4.4a0.dist-info/LICENSE
aa_drifters-0.4.4a0.dist-info/WHEEL
aa_drifters-0.4.4a0.dist-info/METADATA
aa_drifters-0.4.4a0.dist-info/RECORD
