Metadata-Version: 2.3
Name: aa-drifters
Version: 0.4.4a0
Summary: Drifter wormhole tracker/manager plugin for Alliance Auth.
Keywords: allianceauth,eveonline
Author-email: Joel Falknau <joel.falknau@gmail.com>
Requires-Python: >=3.8
Classifier: Environment :: Web Environment
Classifier: Framework :: Celery
Classifier: Framework :: Django
Classifier: Framework :: Django :: 4.0
Classifier: Framework :: Django :: 4.2
Classifier: Intended Audience :: Developers
Classifier: License :: OSI Approved :: MIT License
Classifier: Operating System :: OS Independent
Classifier: Programming Language :: Python
Classifier: Programming Language :: Python :: 3 :: Only
Classifier: Programming Language :: Python :: 3.8
Classifier: Programming Language :: Python :: 3.9
Classifier: Programming Language :: Python :: 3.10
Classifier: Programming Language :: Python :: 3.11
Classifier: Programming Language :: Python :: 3.12
Classifier: Programming Language :: Python :: 3.13
Classifier: Programming Language :: Python :: Implementation :: CPython
Classifier: Topic :: Internet :: WWW/HTTP
Classifier: Topic :: Internet :: WWW/HTTP :: Dynamic Content
Requires-Dist: aa-routing
Requires-Dist: allianceauth>=3,<5
Requires-Dist: django-eveuniverse
Requires-Dist: django-solo>=2,<3
Requires-Dist: py-cord>=2,<3
Requires-Dist: rapidfuzz>=3
Project-URL: Homepage, https://gitlab.com/tactical-supremacy/aa-drifters
Project-URL: Source, https://gitlab.com/tactical-supremacy/aa-drifters
Project-URL: Tracker, https://gitlab.com/tactical-supremacy/aa-drifters/-/issues
